tracardi_discord_webhook/plugin.py
tracardi_discord_webhook/model/configuration.py
tracardi_discord_webhook/model/__pycache__/configuration.cpython-38.pyc
tracardi_discord_webhook/test/manual/discord_webhook_test.py
tracardi_discord_webhook-0.6.0.dist-info/LICENSE.md
tracardi_discord_webhook-0.6.0.dist-info/METADATA
tracardi_discord_webhook-0.6.0.dist-info/WHEEL
tracardi_discord_webhook-0.6.0.dist-info/top_level.txt
tracardi_discord_webhook-0.6.0.dist-info/RECORD
